{"vandevelde_1846.jpeg7259533":{"filename":"vandevelde_1846.jpeg","size":7259533,"regions":[{"shape_attributes":{"name":"polygon","all_points_x":[4191,4198,4361,4354],"all_points_y":[2537,2566,2541,2510]},"region_attributes":{"annotation":"Dome of","multiline_g":"4"}},{"shape_attributes":{"name":"polygon","all_points_x":[4215,4360,4353,4212],"all_points_y":[2592,2575,2544,2559]},"region_attributes":{"annotation":"the Rock","multiline_g":"4"}},{"shape_attributes":{"name":"polygon","all_points_x":[4370,4370,4493,4491],"all_points_y":[2444,2488,2493,2451]},"region_attributes":{"annotation":"Golden","multiline_g":"5"}},{"shape_attributes":{"name":"polygon","all_points_x":[4407,4487,4487,4409],"all_points_y":[2524,2530,2491,2486]},"region_attributes":{"annotation":"Gate","multiline_g":"5"}},{"shape_attributes":{"name":"polygon","all_points_x":[3341,3345,3588,3586],"all_points_y":[2058,2106,2104,2058]},"region_attributes":{"annotation":"Damascus Gate"}},{"shape_attributes":{"name":"polygon","all_points_x":[3500,3500,3659,3661],"all_points_y":[1985,2031,2029,1989]},"region_attributes":{"annotation":"Reservoir"}},{"shape_attributes":{"name":"polygon","all_points_x":[3793,3793,4027,4027],"all_points_y":[1857,1906,1906,1853]},"region_attributes":{"annotation":"Gate of Herod"}},{"shape_attributes":{"name":"polygon","all_points_x":[3958,3957,4221,4222],"all_points_y":[1768,1825,1820,1766]},"region_attributes":{"annotation":"Birket el-Hejjeh"}},{"shape_attributes":{"name":"polygon","all_points_x":[3937,3927,4078,4176,4248,4381,4402,4267,4193,4092],"all_points_y":[1939,1981,2034,2074,2108,2188,2137,2064,2030,1989]},"region_attributes":{"annotation":"Hâret Bâb-el-Hotta"}},{"shape_attributes":{"name":"polygon","all_points_x":[3226,3270,3338,3427,3537,3491,3416,3310,3248],"all_points_y":[2813,2828,2703,2559,2407,2371,2473,2630,2762]},"region_attributes":{"annotation":"CHRISTIAN","multiline_g":"2"}},{"shape_attributes":{"name":"polygon","all_points_x":[3334,3400,3528,3597,3546,3431],"all_points_y":[2784,2809,2594,2477,2444,2623]},"region_attributes":{"annotation":"QUARTER","multiline_g":"2"}},{"shape_attributes":{"name":"polygon","all_points_x":[3290,3347,3407,3480,3597,3546,3431,3356],"all_points_y":[3389,3416,3268,3127,2952,2919,3113,3255]},"region_attributes":{"annotation":"ARMENIAN","multiline_g":"8"}},{"shape_attributes":{"name":"polygon","all_points_x":[3427,3491,3531,3601,3674,3716,3656,3573,3480],"all_points_y":[3369,3398,3288,3168,3051,2994,2954,3080,3252]},"region_attributes":{"annotation":"QUARTER","multiline_g":"8"}},{"shape_attributes":{"name":"polygon","all_points_x":[3725,3789,3822,3829,3842,3780,3773,3751],"all_points_y":[3230,3246,3093,3018,2886,2888,2972,3098]},"region_attributes":{"annotation":"JEWISH","multiline_g":"10"}},{"shape_attributes":{"name":"polygon","all_points_x":[3840,3877,3895,3899,3851,3842,3824,3796,3833],"all_points_y":[3217,3076,2965,2826,2822,2945,3051,3219,3226]},"region_attributes":{"annotation":"QUARTER","multiline_g":"10"}},{"shape_attributes":{"name":"polygon","all_points_x":[3027,3028,3242,3236],"all_points_y":[2854,2903,2899,2848]},"region_attributes":{"annotation":"Yâfa Gate"}},{"shape_attributes":{"name":"polygon","all_points_x":[3152,3154,3313,3308],"all_points_y":[2928,2974,2966,2924]},"region_attributes":{"annotation":"Castle"}},{"shape_attributes":{"name":"polygon","all_points_x":[3301,3321,3385,3467,3443,3365],"all_points_y":[3507,3546,3519,3468,3439,3479]},"region_attributes":{"annotation":"Christian","multiline_g":"9"}},{"shape_attributes":{"name":"polygon","all_points_x":[3307,3363,3421,3478,3458,3387,3334,3304],"all_points_y":[3592,3577,3549,3512,3480,3522,3552,3558]},"region_attributes":{"annotation":"Cemeteries","multiline_g":"9"}},{"shape_attributes":{"name":"polygon","all_points_x":[3354,3356,3621,3613],"all_points_y":[3672,3727,3731,3672]},"region_attributes":{"annotation":"Davids tomb"}},{"shape_attributes":{"name":"polygon","all_points_x":[3491,3493,3671,3666],"all_points_y":[3439,3487,3484,3442]},"region_attributes":{"annotation":"Sion Gate"}},{"shape_attributes":{"name":"polygon","all_points_x":[3852,3661,3664,3854],"all_points_y":[3475,3467,3428,3434]},"region_attributes":{"annotation":"Leper's huts"}},{"shape_attributes":{"name":"polygon","all_points_x":[3517,3517,3737,3736],"all_points_y":[3505,3550,3554,3508]},"region_attributes":{"annotation":"Arm.convent"}},{"shape_attributes":{"name":"polygon","all_points_x":[3747,3782,4051,4091,4335,4292,4050,4000,3827,3741],"all_points_y":[2799,2809,2325,2275,1966,1934,2239,2310,2615,2795]},"region_attributes":{"annotation":"MOHAMMEDAN QUARTER"}},{"shape_attributes":{"name":"polygon","all_points_x":[3588,3589,3909,3904],"all_points_y":[1763,1819,1819,1767]},"region_attributes":{"annotation":"Cave of Jeremiah"}},{"shape_attributes":{"name":"polygon","all_points_x":[4089,4289,4284,4091],"all_points_y":[2332,2315,2283,2296]},"region_attributes":{"annotation":"Pilate's house"}},{"shape_attributes":{"name":"polygon","all_points_x":[4491,4492,4782,4782],"all_points_y":[2075,2116,2109,2073]},"region_attributes":{"annotation":"Birket Hammâm-","multiline_g":"1"}},{"shape_attributes":{"name":"polygon","all_points_x":[4526,4746,4742,4525],"all_points_y":[2144,2140,2105,2110]},"region_attributes":{"annotation":"-Sitti Mariam","multiline_g":"1"}},{"shape_attributes":{"name":"polygon","all_points_x":[4484,4486,4789,4785],"all_points_y":[2177,2226,2228,2177]},"region_attributes":{"annotation":"Sᵗ.Stephen's Gate"}},{"shape_attributes":{"name":"polygon","all_points_x":[4190,4170,4235,4292,4331,4371,4408,4429,4453,4482,4503,4547,4536,4503,4455,4396,4302,4237],"all_points_y":[2358,2394,2432,2475,2503,2546,2587,2622,2676,2745,2834,2830,2765,2671,2579,2524,2439,2390]},"region_attributes":{"annotation":"Haram esh-Sherîf"}},{"shape_attributes":{"name":"polygon","all_points_x":[4302,4312,4462,4457],"all_points_y":[2803,2848,2828,2783]},"region_attributes":{"annotation":"M.el-Aksa"}},{"shape_attributes":{"name":"polygon","all_points_x":[4424,4433,4556,4548],"all_points_y":[2891,2938,2917,2872]},"region_attributes":{"annotation":"Vaults"}},{"shape_attributes":{"name":"polygon","all_points_x":[4369,4377,4564,4555],"all_points_y":[2957,2997,2969,2928]},"region_attributes":{"annotation":"M. of Omar"}},{"shape_attributes":{"name":"polygon","all_points_x":[3972,4005,4095,4058],"all_points_y":[2897,2920,2798,2773]},"region_attributes":{"annotation":"Hâret","multiline_g":"6"}},{"shape_attributes":{"name":"polygon","all_points_x":[3992,4025,4098,4174,4132],"all_points_y":[2942,2970,2892,2774,2745]},"region_attributes":{"annotation":"el-Mogha-","multiline_g":"6"}},{"shape_attributes":{"name":"polygon","all_points_x":[4082,4169,4128,4049,4047],"all_points_y":[2983,2873,2846,2942,2952]},"region_attributes":{"annotation":"-riby","multiline_g":"6"}},{"shape_attributes":{"name":"polygon","all_points_x":[4090,4091,4286,4283],"all_points_y":[3116,3178,3178,3116]},"region_attributes":{"annotation":"Dung Gate"}},{"shape_attributes":{"name":"polygon","all_points_x":[4117,4117,4249,4246],"all_points_y":[3225,3258,3256,3221]},"region_attributes":{"annotation":"Channel","multiline_g":"7"}},{"shape_attributes":{"name":"polygon","all_points_x":[4120,4255,4255,4120],"all_points_y":[3284,3287,3255,3256]},"region_attributes":{"annotation":"entrance","multiline_g":"7"}},{"shape_attributes":{"name":"polygon","all_points_x":[3727,3540,3536,3724],"all_points_y":[2538,2560,2521,2507]},"region_attributes":{"annotation":"Church of the","multiline_g":"3"}},{"shape_attributes":{"name":"polygon","all_points_x":[3675,3523,3516,3675],"all_points_y":[2581,2601,2557,2544]},"region_attributes":{"annotation":"Sepulchre","multiline_g":"3"}},{"shape_attributes":{"name":"polygon","all_points_x":[3068,3099,3105,3091,3068,3076,3066,3051],"all_points_y":[2607,2548,2496,2483,2495,2512,2548,2586]},"region_attributes":{"annotation":"ruins"}},{"shape_attributes":{"name":"polygon","all_points_x":[3120,3136,3194,3251,3234],"all_points_y":[2481,2524,2487,2448,2414]},"region_attributes":{"annotation":"Fields"}},{"shape_attributes":{"name":"polygon","all_points_x":[3233,3275,3297,3317,3336,3357,3342,3329,3300,3280,3258],"all_points_y":[2493,2501,2499,2491,2483,2467,2440,2454,2459,2458,2448]},"region_attributes":{"annotation":"Ruins"}},{"shape_attributes":{"name":"polygon","all_points_x":[3411,3438,3573,3544],"all_points_y":[2279,2314,2193,2161]},"region_attributes":{"annotation":"Fields"}},{"shape_attributes":{"name":"polygon","all_points_x":[3780,3774,3827,3891,3922,3904,3863,3825],"all_points_y":[1961,2008,2007,1998,1987,1943,1959,1963]},"region_attributes":{"annotation":"Ruins"}},{"shape_attributes":{"name":"polygon","all_points_x":[3516,3550,3518,3492],"all_points_y":[2819,2817,2585,2592]},"region_attributes":{"annotation":"H.en-Nassara"}},{"shape_attributes":{"name":"polygon","all_points_x":[3666,3703,3690,3662],"all_points_y":[2828,2833,2722,2727]},"region_attributes":{"annotation":"Bazars"}},{"shape_attributes":{"name":"polygon","all_points_x":[3823,3831,3862,3855],"all_points_y":[2358,2386,2377,2353]},"region_attributes":{"annotation":"10"}},{"shape_attributes":{"name":"polygon","all_points_x":[3957,3961,3984,3981],"all_points_y":[2300,2325,2321,2297]},"region_attributes":{"annotation":"11"}},{"shape_attributes":{"name":"polygon","all_points_x":[4196,4200,4227,4223],"all_points_y":[2252,2276,2273,2250]},"region_attributes":{"annotation":"11"}},{"shape_attributes":{"name":"polygon","all_points_x":[4363,4368,4405,4401],"all_points_y":[2271,2298,2291,2264]},"region_attributes":{"annotation":"12"}},{"shape_attributes":{"name":"polygon","all_points_x":[3882,3894,3924,3913],"all_points_y":[2450,2480,2463,2443]},"region_attributes":{"annotation":"10"}},{"shape_attributes":{"name":"polygon","all_points_x":[3934,3965,3960,3932],"all_points_y":[2601,2594,2568,2574]},"region_attributes":{"annotation":"10"}},{"shape_attributes":{"name":"polygon","all_points_x":[3962,3968,4000,3994],"all_points_y":[2715,2744,2737,2708]},"region_attributes":{"annotation":"10"}},{"shape_attributes":{"name":"polygon","all_points_x":[3455,3460,3487,3480],"all_points_y":[2764,2794,2791,2761]},"region_attributes":{"annotation":"4"}},{"shape_attributes":{"name":"polygon","all_points_x":[3589,3596,3623,3614],"all_points_y":[2734,2765,2760,2734]},"region_attributes":{"annotation":"5"}},{"shape_attributes":{"name":"polygon","all_points_x":[4271,4257,4312,4359,4408,4433,4392,4319],"all_points_y":[1810,1851,1865,1881,1909,1875,1845,1824]},"region_attributes":{"annotation":"Fields"}},{"shape_attributes":{"name":"polygon","all_points_x":[4072,4074,4165,4161],"all_points_y":[1561,1603,1600,1558]},"region_attributes":{"annotation":"tank"}},{"shape_attributes":{"name":"polygon","all_points_x":[4314,4316,4392,4389],"all_points_y":[1493,1533,1529,1488]},"region_attributes":{"annotation":"ruin"}},{"shape_attributes":{"name":"polygon","all_points_x":[4070,4071,4157,4159],"all_points_y":[1679,1725,1729,1682]},"region_attributes":{"annotation":"ruin"}},{"shape_attributes":{"name":"polygon","all_points_x":[3289,3419,3418,3293],"all_points_y":[1802,1804,1762,1757]},"region_attributes":{"annotation":"Ouarry"}},{"shape_attributes":{"name":"polygon","all_points_x":[3491,3492,3586,3585],"all_points_y":[1627,1667,1667,1624]},"region_attributes":{"annotation":"tanks"}},{"shape_attributes":{"name":"polygon","all_points_x":[3581,3595,3661,3729,3782,3843,3886,3904,3788,3715,3621],"all_points_y":[1700,1732,1714,1704,1710,1721,1743,1712,1664,1661,1685]},"region_attributes":{"annotation":"Moham ḍṇ tombs"}},{"shape_attributes":{"name":"polygon","all_points_x":[4142,4137,4099,4104],"all_points_y":[1989,1959,1959,1987]},"region_attributes":{"annotation":"14"}},{"shape_attributes":{"name":"polygon","all_points_x":[4288,4339,4394,4418,4367,4308],"all_points_y":[1916,1930,1963,1940,1906,1884]},"region_attributes":{"annotation":"ruins"}},{"shape_attributes":{"name":"polygon","all_points_x":[3250,3252,3271,3268],"all_points_y":[2628,2658,2658,2627]},"region_attributes":{"annotation":"6"}},{"shape_attributes":{"name":"polygon","all_points_x":[3274,3274,3295,3295],"all_points_y":[2516,2548,2546,2514]},"region_attributes":{"annotation":"7"}},{"shape_attributes":{"name":"polygon","all_points_x":[3793,3797,3814,3810],"all_points_y":[2435,2461,2460,2431]},"region_attributes":{"annotation":"9"}},{"shape_attributes":{"name":"polygon","all_points_x":[3700,3740,3752,3765,3776,3761,3719,3728,3732,3728,3719],"all_points_y":[3156,3169,3089,3031,2976,2872,2883,2946,2991,3034,3096]},"region_attributes":{"annotation":"Suk H.el-Jehud"}},{"shape_attributes":{"name":"polygon","all_points_x":[4225,4239,4547,4533],"all_points_y":[2707,2789,2749,2665]},"region_attributes":{"annotation":"MORIAH"}},{"shape_attributes":{"name":"polygon","all_points_x":[4185,4217,4323,4291],"all_points_y":[3081,3112,3017,2990]},"region_attributes":{"annotation":"Garden"}},{"shape_attributes":{"name":"polygon","all_points_x":[3526,3597,3595,3530],"all_points_y":[3339,3339,3302,3304]},"region_attributes":{"annotation":"Mill"}},{"shape_attributes":{"name":"polygon","all_points_x":[4426,4395,4389,4420],"all_points_y":[2146,2152,2131,2125]},"region_attributes":{"annotation":"13","multiline_g":""}},{"shape_attributes":{"name":"polygon","all_points_x":[3309,3384,3384,3309],"all_points_y":[1563,1561,1598,1598]},"region_attributes":{"annotation":"tank"}},{"shape_attributes":{"name":"polygon","all_points_x":[3042,3067,3088,3116,3159,3158,3105,3079,3051],"all_points_y":[3369,3395,3368,3358,3351,3298,3309,3326,3354]},"region_attributes":{"annotation":"bridge"}},{"shape_attributes":{"name":"polygon","all_points_x":[4247,4271,4304,4314,4334,4360,4371,4379,4347,4337,4333,4307,4264],"all_points_y":[3623,3663,3625,3600,3591,3568,3538,3505,3491,3523,3548,3569,3611]},"region_attributes":{"annotation":"channel"}},{"shape_attributes":{"name":"polygon","all_points_x":[3465,3465,3487,3487],"all_points_y":[2959,2990,2987,2958]},"region_attributes":{"annotation":"1"}},{"shape_attributes":{"name":"polygon","all_points_x":[3629,3632,3662,3658],"all_points_y":[2922,2956,2954,2922]},"region_attributes":{"annotation":"3"}},{"shape_attributes":{"name":"polygon","all_points_x":[3472,3476,3498,3495],"all_points_y":[3190,3218,3216,3187]},"region_attributes":{"annotation":"2"}},{"shape_attributes":{"name":"polygon","all_points_x":[3355,3284,3330,3394],"all_points_y":[3151,3348,3376,3163]},"region_attributes":{"annotation":"Garden"}},{"shape_attributes":{"name":"polygon","all_points_x":[4299,4299,4490,4489],"all_points_y":[3295,3331,3343,3295]},"region_attributes":{"annotation":"Fountain of","multiline_g":"11"}},{"shape_attributes":{"name":"polygon","all_points_x":[4304,4458,4458,4305],"all_points_y":[3365,3374,3337,3328]},"region_attributes":{"annotation":"the Virgin","multiline_g":"11"}},{"shape_attributes":{"name":"polygon","all_points_x":[4277,4279,4406,4402],"all_points_y":[3364,3401,3397,3365]},"region_attributes":{"annotation":"Channel","multiline_g":"12"}},{"shape_attributes":{"name":"polygon","all_points_x":[4287,4377,4373,4286],"all_points_y":[3429,3426,3395,3397]},"region_attributes":{"annotation":"outlet","multiline_g":"12"}}],"file_attributes":{}}}